pyalogflow/__init__.py
pyalogflow/pyalogflow.py
pyalogflow-1.1.4.dist-info/AUTHORS.rst
pyalogflow-1.1.4.dist-info/LICENSE.txt
pyalogflow-1.1.4.dist-info/METADATA
pyalogflow-1.1.4.dist-info/WHEEL
pyalogflow-1.1.4.dist-info/top_level.txt
pyalogflow-1.1.4.dist-info/RECORD
